volume_density_mapper/__init__.py
volume_density_mapper/density_reconstruction.py
volume_density_mapper-0.1.0.dist-info/METADATA
volume_density_mapper-0.1.0.dist-info/WHEEL
volume_density_mapper-0.1.0.dist-info/top_level.txt
volume_density_mapper-0.1.0.dist-info/RECORD
