Metadata-Version: 2.4
Name: volume-density-mapper
Version: 0.1.0
Summary: Reconstructs 3D density distributions from 2D column density maps using constrained diffusion.
Author-email: Guang-Xing Li <ligx.ngc7293@gmail.com>
Requires-Python: >=3.8
Requires-Dist: numpy>=1.0.0
Requires-Dist: scipy>=1.0.0
Requires-Dist: constrained-diffusion>=0.1.0
